lilliepy_protect/__init__.py
lilliepy_protect/main.py
lilliepy_protect-1.0.dist-info/METADATA
lilliepy_protect-1.0.dist-info/WHEEL
lilliepy_protect-1.0.dist-info/top_level.txt
lilliepy_protect-1.0.dist-info/RECORD
