Metadata-Version: 2.2
Name: lilliepy-protect
Version: 1.0
Summary: A protection decorator to protect components
Home-page: https://github.com/websitedeb/lilliept-protect
Author: sarthak ghoshal
Author-email: sarthak22.ghoshal@gmail.com
Keywords: reactpy,lilliepy,lilliepy_protect
Classifier: Programming Language :: Python :: 3
Classifier: License :: OSI Approved :: MIT License
Classifier: Operating System :: OS Independent
Requires-Python: >=3.7
Requires-Dist: reactpy
Requires-Dist: reactpy_router
Dynamic: author
Dynamic: author-email
Dynamic: classifier
Dynamic: description
Dynamic: description-content-type
Dynamic: home-page
Dynamic: keywords
Dynamic: requires-dist
Dynamic: requires-python
Dynamic: summary
